{"source": "estimation OSM Paris 2023 (repli)", "arrondissements": {"1": {"supermarches": 0, "pharmacies": 0, "boulangeries": 0, "centres_commerciaux": 0}, "2": {"supermarches": 8, "pharmacies": 18, "boulangeries": 22, "centres_commerciaux": 2}, "3": {"supermarches": 6, "pharmacies": 14, "boulangeries": 18, "centres_commerciaux": 1}, "4": {"supermarches": 10, "pharmacies": 16, "boulangeries": 20, "centres_commerciaux": 1}, "5": {"supermarches": 9, "pharmacies": 17, "boulangeries": 21, "centres_commerciaux": 2}, "6": {"supermarches": 11, "pharmacies": 19, "boulangeries": 24, "centres_commerciaux": 1}, "7": {"supermarches": 10, "pharmacies": 18, "boulangeries": 22, "centres_commerciaux": 1}, "8": {"supermarches": 12, "pharmacies": 20, "boulangeries": 26, "centres_commerciaux": 2}, "9": {"supermarches": 14, "pharmacies": 22, "boulangeries": 28, "centres_commerciaux": 4}, "10": {"supermarches": 16, "pharmacies": 24, "boulangeries": 30, "centres_commerciaux": 2}, "11": {"supermarches": 18, "pharmacies": 26, "boulangeries": 32, "centres_commerciaux": 3}, "12": {"supermarches": 20, "pharmacies": 28, "boulangeries": 35, "centres_commerciaux": 2}, "13": {"supermarches": 22, "pharmacies": 24, "boulangeries": 38, "centres_commerciaux": 3}, "14": {"supermarches": 24, "pharmacies": 26, "boulangeries": 40, "centres_commerciaux": 4}, "15": {"supermarches": 20, "pharmacies": 22, "boulangeries": 36, "centres_commerciaux": 2}, "16": {"supermarches": 26, "pharmacies": 28, "boulangeries": 42, "centres_commerciaux": 3}, "17": {"supermarches": 18, "pharmacies": 20, "boulangeries": 34, "centres_commerciaux": 3}, "18": {"supermarches": 22, "pharmacies": 24, "boulangeries": 38, "centres_commerciaux": 2}, "19": {"supermarches": 24, "pharmacies": 26, "boulangeries": 40, "centres_commerciaux": 2}, "20": {"supermarches": 20, "pharmacies": 22, "boulangeries": 36, "centres_commerciaux": 1}, "21": {"supermarches": 22, "pharmacies": 24, "boulangeries": 38, "centres_commerciaux": 2}}}